whiterose.py
whiterose-0.1.7.dist-info/LICENSE
whiterose-0.1.7.dist-info/METADATA
whiterose-0.1.7.dist-info/WHEEL
whiterose-0.1.7.dist-info/top_level.txt
whiterose-0.1.7.dist-info/RECORD
