Metadata-Version: 2.1
Name: whiterose
Version: 0.1.7
Summary: Whiterose is a pure Python library built to return the current time in real-time within a single stdout. This Python library does not require any external libraries.
Home-page: https://github.com/battleoverflow/whiterose
Author: battleoverflow
Classifier: Programming Language :: Python :: 3
Classifier: License :: OSI Approved :: MIT License
Classifier: Operating System :: OS Independent
Requires-Python: >=3.6
License-File: LICENSE
